<?xml version="1.0" encoding="UTF-8" standalone="no"?>
<galaxy>
    <star blackHole="false" name="Celesta" numGasGiants="0" numPlanets="0" size="1.0" temp="100" x="0" y="0">
        <planet DIMID="0" customIcon="earthlike" dimMapping="" name="Terra">
            <isKnown>true</isKnown>
            <fogColor>1.0,1.0,1.0</fogColor>
            <skyColor>1.0,1.0,1.0</skyColor>
            <gravitationalMultiplier>100</gravitationalMultiplier>
            <orbitalDistance>100</orbitalDistance>
            <orbitalTheta>0</orbitalTheta>
            <orbitalPhi>0</orbitalPhi>
            <avgTemperature>255</avgTemperature>
            <rotationalPeriod>24000</rotationalPeriod>
            <atmosphereDensity>90</atmosphereDensity>
            <generateCraters>false</generateCraters>
            <generateVolcanos>false</generateVolcanos>
            <generateStructures>false</generateStructures>
            <generateGeodes>false</generateGeodes>
            <planet DIMID="145" customIcon="moon" name="Luna">
                <isKnown>true</isKnown>
                <fogColor>1.0,1.0,1.0</fogColor>
                <skyColor>1.0,1.0,1.0</skyColor>
                <gravitationalMultiplier>16</gravitationalMultiplier>
                <orbitalDistance>100</orbitalDistance>
                <orbitalTheta>0</orbitalTheta>
                <orbitalPhi>0</orbitalPhi>
                <avgTemperature>255</avgTemperature>
                <rotationalPeriod>72000</rotationalPeriod>
                <atmosphereDensity>0</atmosphereDensity>
                <generateCraters>false</generateCraters>
                <generateVolcanos>false</generateVolcanos>
                <generateStructures>false</generateStructures>
                <generateGeodes>false</generateGeodes>
                <biomeIds>advancedrocketry:moon,advancedrocketry:moondark</biomeIds>
            </planet>
        </planet>
        <planet DIMID="160" name="Sol-160">
            <isKnown>false</isKnown>
            <GasGiant>true</GasGiant>
            <gas>hydrogen</gas>
            <gas>oxygen</gas>
            <gas>nitrogen</gas>
            <fogColor>1.0,1.0,1.0</fogColor>
            <skyColor>1.0,1.0,1.0</skyColor>
            <gravitationalMultiplier>97</gravitationalMultiplier>
            <orbitalDistance>204</orbitalDistance>
            <orbitalTheta>0</orbitalTheta>
            <orbitalPhi>0</orbitalPhi>
            <avgTemperature>201</avgTemperature>
            <rotationalPeriod>24000</rotationalPeriod>
            <atmosphereDensity>124</atmosphereDensity>
            <generateCraters>false</generateCraters>
            <generateVolcanos>false</generateVolcanos>
            <generateStructures>false</generateStructures>
            <generateGeodes>false</generateGeodes>
        </planet>
        <planet DIMID="161" name="Sol-161">
            <isKnown>false</isKnown>
            <GasGiant>true</GasGiant>
            <gas>hydrogen</gas>
            <gas>oxygen</gas>
            <gas>nitrogen</gas>
            <fogColor>1.0,1.0,1.0</fogColor>
            <skyColor>1.0,1.0,1.0</skyColor>
            <gravitationalMultiplier>130</gravitationalMultiplier>
            <orbitalDistance>267</orbitalDistance>
            <orbitalTheta>0</orbitalTheta>
            <orbitalPhi>0</orbitalPhi>
            <avgTemperature>176</avgTemperature>
            <rotationalPeriod>24000</rotationalPeriod>
            <atmosphereDensity>103</atmosphereDensity>
            <generateCraters>false</generateCraters>
            <generateVolcanos>false</generateVolcanos>
            <generateStructures>false</generateStructures>
            <generateGeodes>false</generateGeodes>
            <planet DIMID="162" name="Sol-161: 0">
                <isKnown>false</isKnown>
                <fogColor>1.0,1.0,1.0</fogColor>
                <skyColor>0.8,0.72315985,0.95783824</skyColor>
                <gravitationalMultiplier>70</gravitationalMultiplier>
                <orbitalDistance>161</orbitalDistance>
                <orbitalTheta>347</orbitalTheta>
                <orbitalPhi>-52</orbitalPhi>
                <avgTemperature>201</avgTemperature>
                <rotationalPeriod>69970</rotationalPeriod>
                <atmosphereDensity>32</atmosphereDensity>
                <generateCraters>true</generateCraters>
                <generateVolcanos>false</generateVolcanos>
                <generateStructures>false</generateStructures>
                <generateGeodes>false</generateGeodes>
                <craterFrequencyMultiplier>1.0</craterFrequencyMultiplier>
                <biomeIds>traverse:canyon,minecraft:stone_beach,traverse:lush_hills,minecraft:mesa_rock,advancedrocketry:volcanicbarren</biomeIds>
            </planet>
        </planet>
        <planet DIMID="163" name="Sol-163">
            <isKnown>false</isKnown>
            <GasGiant>true</GasGiant>
            <gas>hydrogen</gas>
            <gas>oxygen</gas>
            <gas>nitrogen</gas>
            <fogColor>1.0,1.0,1.0</fogColor>
            <skyColor>1.0,1.0,1.0</skyColor>
            <gravitationalMultiplier>130</gravitationalMultiplier>
            <orbitalDistance>210</orbitalDistance>
            <orbitalTheta>0</orbitalTheta>
            <orbitalPhi>0</orbitalPhi>
            <avgTemperature>198</avgTemperature>
            <rotationalPeriod>24000</rotationalPeriod>
            <atmosphereDensity>112</atmosphereDensity>
            <generateCraters>false</generateCraters>
            <generateVolcanos>false</generateVolcanos>
            <generateStructures>false</generateStructures>
            <generateGeodes>false</generateGeodes>
            <planet DIMID="164" name="Sol-163: 0">
                <isKnown>false</isKnown>
                <fogColor>1.0,1.0,1.0</fogColor>
                <skyColor>0.8,0.97533226,0.95214516</skyColor>
                <gravitationalMultiplier>52</gravitationalMultiplier>
                <orbitalDistance>149</orbitalDistance>
                <orbitalTheta>267</orbitalTheta>
                <orbitalPhi>-141</orbitalPhi>
                <avgTemperature>209</avgTemperature>
                <rotationalPeriod>161206</rotationalPeriod>
                <atmosphereDensity>31</atmosphereDensity>
                <generateCraters>true</generateCraters>
                <generateVolcanos>false</generateVolcanos>
                <generateStructures>false</generateStructures>
                <generateGeodes>false</generateGeodes>
                <craterFrequencyMultiplier>1.0</craterFrequencyMultiplier>
                <biomeIds>minecraft:smaller_extreme_hills,minecraft:jungle_edge,minecraft:mesa,traverse:canyon,traverse:rocky_plains</biomeIds>
            </planet>
            <planet DIMID="165" name="Sol-163: 1">
                <isKnown>false</isKnown>
                <fogColor>1.0,1.0,1.0</fogColor>
                <skyColor>0.8,0.5494753,1.0</skyColor>
                <gravitationalMultiplier>75</gravitationalMultiplier>
                <orbitalDistance>194</orbitalDistance>
                <orbitalTheta>221</orbitalTheta>
                <orbitalPhi>-145</orbitalPhi>
                <avgTemperature>183</avgTemperature>
                <rotationalPeriod>56888</rotationalPeriod>
                <atmosphereDensity>15</atmosphereDensity>
                <generateCraters>true</generateCraters>
                <generateVolcanos>false</generateVolcanos>
                <generateStructures>false</generateStructures>
                <generateGeodes>false</generateGeodes>
                <craterFrequencyMultiplier>1.0</craterFrequencyMultiplier>
                <biomeIds>advancedrocketry:moon,advancedrocketry:moondark</biomeIds>
            </planet>
            <planet DIMID="166" name="Sol-163: 2">
                <isKnown>false</isKnown>
                <fogColor>1.0,1.0,1.0</fogColor>
                <skyColor>0.8,0.6971478,1.0</skyColor>
                <gravitationalMultiplier>71</gravitationalMultiplier>
                <orbitalDistance>172</orbitalDistance>
                <orbitalTheta>238</orbitalTheta>
                <orbitalPhi>-215</orbitalPhi>
                <avgTemperature>195</avgTemperature>
                <rotationalPeriod>67055</rotationalPeriod>
                <atmosphereDensity>27</atmosphereDensity>
                <generateCraters>true</generateCraters>
                <generateVolcanos>false</generateVolcanos>
                <generateStructures>false</generateStructures>
                <generateGeodes>false</generateGeodes>
                <craterFrequencyMultiplier>1.0</craterFrequencyMultiplier>
                <biomeIds>minecraft:smaller_extreme_hills,minecraft:mutated_forest,minecraft:mutated_birch_forest,minecraft:jungle,minecraft:mesa_clear_rock</biomeIds>
            </planet>
            <planet DIMID="167" name="Sol-163: 3">
                <isKnown>false</isKnown>
                <fogColor>1.0,1.0,1.0</fogColor>
                <skyColor>0.8,0.9377545,0.9201487</skyColor>
                <gravitationalMultiplier>49</gravitationalMultiplier>
                <orbitalDistance>120</orbitalDistance>
                <orbitalTheta>359</orbitalTheta>
                <orbitalPhi>-170</orbitalPhi>
                <avgTemperature>233</avgTemperature>
                <rotationalPeriod>203996</rotationalPeriod>
                <atmosphereDensity>31</atmosphereDensity>
                <generateCraters>true</generateCraters>
                <generateVolcanos>false</generateVolcanos>
                <generateStructures>false</generateStructures>
                <generateGeodes>false</generateGeodes>
                <craterFrequencyMultiplier>1.0</craterFrequencyMultiplier>
                <biomeIds>traverse:canyon,traverse:autumnal_wooded_hills,traverse:rocky_plains,minecraft:roofed_forest,traverse:woodlands</biomeIds>
            </planet>
            <planet DIMID="168" name="Sol-163: 4">
                <isKnown>false</isKnown>
                <fogColor>1.0,1.0,1.0</fogColor>
                <skyColor>0.8,0.6195755,1.0</skyColor>
                <gravitationalMultiplier>57</gravitationalMultiplier>
                <orbitalDistance>198</orbitalDistance>
                <orbitalTheta>263</orbitalTheta>
                <orbitalPhi>-155</orbitalPhi>
                <avgTemperature>181</avgTemperature>
                <rotationalPeriod>129594</rotationalPeriod>
                <atmosphereDensity>14</atmosphereDensity>
                <generateCraters>true</generateCraters>
                <generateVolcanos>false</generateVolcanos>
                <generateStructures>false</generateStructures>
                <generateGeodes>false</generateGeodes>
                <craterFrequencyMultiplier>1.0</craterFrequencyMultiplier>
                <biomeIds>advancedrocketry:moon,advancedrocketry:moondark</biomeIds>
            </planet>
        </planet>
        <planet DIMID="100" customIcon="earthlike" dimMapping="" name="Nova">
            <isKnown>true</isKnown>
            <fogColor>1.0,1.0,1.0</fogColor>
            <skyColor>1.0,1.0,1.0</skyColor>
            <gravitationalMultiplier>100</gravitationalMultiplier>
            <orbitalDistance>110</orbitalDistance>
            <orbitalTheta>0</orbitalTheta>
            <orbitalPhi>0</orbitalPhi>
            <avgTemperature>274</avgTemperature>
            <rotationalPeriod>24000</rotationalPeriod>
            <atmosphereDensity>100</atmosphereDensity>
            <generateCraters>false</generateCraters>
            <generateVolcanos>false</generateVolcanos>
            <generateStructures>false</generateStructures>
            <generateGeodes>false</generateGeodes>
        </planet>
        <planet DIMID="173" name="Sol-173">
            <isKnown>false</isKnown>
            <GasGiant>true</GasGiant>
            <gas>hydrogen</gas>
            <gas>oxygen</gas>
            <gas>nitrogen</gas>
            <fogColor>1.0,1.0,1.0</fogColor>
            <skyColor>1.0,1.0,1.0</skyColor>
            <gravitationalMultiplier>107</gravitationalMultiplier>
            <orbitalDistance>190</orbitalDistance>
            <orbitalTheta>0</orbitalTheta>
            <orbitalPhi>0</orbitalPhi>
            <avgTemperature>208</avgTemperature>
            <rotationalPeriod>24000</rotationalPeriod>
            <atmosphereDensity>168</atmosphereDensity>
            <generateCraters>false</generateCraters>
            <generateVolcanos>false</generateVolcanos>
            <generateStructures>false</generateStructures>
            <generateGeodes>false</generateGeodes>
        </planet>
        <planet DIMID="174" name="Sol-174">
            <isKnown>false</isKnown>
            <GasGiant>true</GasGiant>
            <gas>hydrogen</gas>
            <gas>oxygen</gas>
            <gas>nitrogen</gas>
            <fogColor>1.0,1.0,1.0</fogColor>
            <skyColor>1.0,1.0,1.0</skyColor>
            <gravitationalMultiplier>130</gravitationalMultiplier>
            <orbitalDistance>190</orbitalDistance>
            <orbitalTheta>0</orbitalTheta>
            <orbitalPhi>0</orbitalPhi>
            <avgTemperature>208</avgTemperature>
            <rotationalPeriod>24000</rotationalPeriod>
            <atmosphereDensity>133</atmosphereDensity>
            <generateCraters>false</generateCraters>
            <generateVolcanos>false</generateVolcanos>
            <generateStructures>false</generateStructures>
            <generateGeodes>false</generateGeodes>
            <planet DIMID="176" name="Sol-174: 1">
                <isKnown>false</isKnown>
                <fogColor>1.0,1.0,1.0</fogColor>
                <skyColor>0.8,0.6592025,0.81940913</skyColor>
                <gravitationalMultiplier>64</gravitationalMultiplier>
                <orbitalDistance>113</orbitalDistance>
                <orbitalTheta>104</orbitalTheta>
                <orbitalPhi>91</orbitalPhi>
                <avgTemperature>252</avgTemperature>
                <rotationalPeriod>91552</rotationalPeriod>
                <atmosphereDensity>19</atmosphereDensity>
                <generateCraters>true</generateCraters>
                <generateVolcanos>false</generateVolcanos>
                <generateStructures>false</generateStructures>
                <generateGeodes>false</generateGeodes>
                <craterFrequencyMultiplier>1.0</craterFrequencyMultiplier>
                <biomeIds>advancedrocketry:moon,advancedrocketry:moondark</biomeIds>
            </planet>
            <planet DIMID="177" name="Sol-174: 2">
                <isKnown>false</isKnown>
                <fogColor>1.0,1.0,1.0</fogColor>
                <skyColor>0.8,0.778373,0.83107543</skyColor>
                <gravitationalMultiplier>82</gravitationalMultiplier>
                <orbitalDistance>113</orbitalDistance>
                <orbitalTheta>158</orbitalTheta>
                <orbitalPhi>-166</orbitalPhi>
                <avgTemperature>252</avgTemperature>
                <rotationalPeriod>43528</rotationalPeriod>
                <atmosphereDensity>14</atmosphereDensity>
                <generateCraters>true</generateCraters>
                <generateVolcanos>false</generateVolcanos>
                <generateStructures>false</generateStructures>
                <generateGeodes>false</generateGeodes>
                <craterFrequencyMultiplier>1.0</craterFrequencyMultiplier>
                <biomeIds>advancedrocketry:moon,advancedrocketry:moondark</biomeIds>
            </planet>
            <planet DIMID="175" name="Sol-174: 0">
                <isKnown>false</isKnown>
                <hasRings>true</hasRings>
                <ringColor>0.8,0.5533583,0.9189957</ringColor>
                <fogColor>1.0,1.0,1.0</fogColor>
                <skyColor>0.8,0.5533583,0.9189957</skyColor>
                <gravitationalMultiplier>84</gravitationalMultiplier>
                <orbitalDistance>158</orbitalDistance>
                <orbitalTheta>359</orbitalTheta>
                <orbitalPhi>-281</orbitalPhi>
                <avgTemperature>213</avgTemperature>
                <rotationalPeriod>40492</rotationalPeriod>
                <atmosphereDensity>16</atmosphereDensity>
                <generateCraters>true</generateCraters>
                <generateVolcanos>false</generateVolcanos>
                <generateStructures>false</generateStructures>
                <generateGeodes>false</generateGeodes>
                <craterFrequencyMultiplier>1.0</craterFrequencyMultiplier>
                <biomeIds>advancedrocketry:moon,advancedrocketry:moondark</biomeIds>
            </planet>
        </planet>
        <planet DIMID="150" name="Sol-150">
            <isKnown>false</isKnown>
            <GasGiant>true</GasGiant>
            <gas>hydrogen</gas>
            <gas>oxygen</gas>
            <gas>nitrogen</gas>
            <fogColor>1.0,1.0,1.0</fogColor>
            <skyColor>1.0,1.0,1.0</skyColor>
            <gravitationalMultiplier>130</gravitationalMultiplier>
            <orbitalDistance>267</orbitalDistance>
            <orbitalTheta>0</orbitalTheta>
            <orbitalPhi>0</orbitalPhi>
            <avgTemperature>176</avgTemperature>
            <rotationalPeriod>24000</rotationalPeriod>
            <atmosphereDensity>172</atmosphereDensity>
            <generateCraters>false</generateCraters>
            <generateVolcanos>false</generateVolcanos>
            <generateStructures>false</generateStructures>
            <generateGeodes>false</generateGeodes>
            <planet DIMID="151" name="Sol-150: 0">
                <isKnown>false</isKnown>
                <fogColor>1.0,1.0,1.0</fogColor>
                <skyColor>0.8,0.7343061,1.0</skyColor>
                <gravitationalMultiplier>58</gravitationalMultiplier>
                <orbitalDistance>188</orbitalDistance>
                <orbitalTheta>267</orbitalTheta>
                <orbitalPhi>-101</orbitalPhi>
                <avgTemperature>186</avgTemperature>
                <rotationalPeriod>116857</rotationalPeriod>
                <atmosphereDensity>33</atmosphereDensity>
                <generateCraters>true</generateCraters>
                <generateVolcanos>false</generateVolcanos>
                <generateStructures>false</generateStructures>
                <generateGeodes>false</generateGeodes>
                <craterFrequencyMultiplier>1.0</craterFrequencyMultiplier>
                <biomeIds>minecraft:mesa_rock,minecraft:savanna_rock,minecraft:jungle_edge,traverse:rocky_plateau,minecraft:desert</biomeIds>
            </planet>
            <planet DIMID="152" name="Sol-150: 1">
                <isKnown>false</isKnown>
                <fogColor>1.0,1.0,1.0</fogColor>
                <skyColor>0.8,0.98024344,0.87902015</skyColor>
                <gravitationalMultiplier>69</gravitationalMultiplier>
                <orbitalDistance>107</orbitalDistance>
                <orbitalTheta>287</orbitalTheta>
                <orbitalPhi>-76</orbitalPhi>
                <avgTemperature>247</avgTemperature>
                <rotationalPeriod>73057</rotationalPeriod>
                <atmosphereDensity>15</atmosphereDensity>
                <generateCraters>true</generateCraters>
                <generateVolcanos>false</generateVolcanos>
                <generateStructures>false</generateStructures>
                <generateGeodes>false</generateGeodes>
                <craterFrequencyMultiplier>1.0</craterFrequencyMultiplier>
                <biomeIds>advancedrocketry:moon,advancedrocketry:moondark</biomeIds>
            </planet>
            <planet DIMID="153" name="Sol-150: 2">
                <isKnown>false</isKnown>
                <fogColor>1.0,1.0,1.0</fogColor>
                <skyColor>0.8,0.67087066,0.95002353</skyColor>
                <gravitationalMultiplier>77</gravitationalMultiplier>
                <orbitalDistance>159</orbitalDistance>
                <orbitalTheta>191</orbitalTheta>
                <orbitalPhi>-151</orbitalPhi>
                <avgTemperature>202</avgTemperature>
                <rotationalPeriod>52570</rotationalPeriod>
                <atmosphereDensity>16</atmosphereDensity>
                <generateCraters>true</generateCraters>
                <generateVolcanos>false</generateVolcanos>
                <generateStructures>false</generateStructures>
                <generateGeodes>false</generateGeodes>
                <craterFrequencyMultiplier>1.0</craterFrequencyMultiplier>
                <seaLevel>81</seaLevel>
                <biomeIds>advancedrocketry:moon,advancedrocketry:moondark</biomeIds>
            </planet>
            <planet DIMID="154" name="Sol-150: 3">
                <isKnown>false</isKnown>
                <fogColor>1.0,1.0,1.0</fogColor>
                <skyColor>0.8,0.7757406,0.8023852</skyColor>
                <gravitationalMultiplier>85</gravitationalMultiplier>
                <orbitalDistance>99</orbitalDistance>
                <orbitalTheta>31</orbitalTheta>
                <orbitalPhi>-233</orbitalPhi>
                <avgTemperature>257</avgTemperature>
                <rotationalPeriod>39079</rotationalPeriod>
                <atmosphereDensity>22</atmosphereDensity>
                <generateCraters>true</generateCraters>
                <generateVolcanos>false</generateVolcanos>
                <generateStructures>false</generateStructures>
                <generateGeodes>false</generateGeodes>
                <craterFrequencyMultiplier>1.0</craterFrequencyMultiplier>
                <seaLevel>77</seaLevel>
                <biomeIds>advancedrocketry:moon,advancedrocketry:moondark</biomeIds>
                <oceanBlock>advancedrocketry:oxygenfluid</oceanBlock>
            </planet>
        </planet>
        <planet DIMID="155" name="Sol-155">
            <isKnown>false</isKnown>
            <GasGiant>true</GasGiant>
            <gas>hydrogen</gas>
            <gas>oxygen</gas>
            <gas>nitrogen</gas>
            <fogColor>1.0,1.0,1.0</fogColor>
            <skyColor>1.0,1.0,1.0</skyColor>
            <gravitationalMultiplier>130</gravitationalMultiplier>
            <orbitalDistance>245</orbitalDistance>
            <orbitalTheta>0</orbitalTheta>
            <orbitalPhi>0</orbitalPhi>
            <avgTemperature>183</avgTemperature>
            <rotationalPeriod>24000</rotationalPeriod>
            <atmosphereDensity>140</atmosphereDensity>
            <generateCraters>false</generateCraters>
            <generateVolcanos>false</generateVolcanos>
            <generateStructures>false</generateStructures>
            <generateGeodes>false</generateGeodes>
        </planet>
        <planet DIMID="156" name="Sol-156">
            <isKnown>false</isKnown>
            <GasGiant>true</GasGiant>
            <gas>hydrogen</gas>
            <gas>oxygen</gas>
            <gas>nitrogen</gas>
            <fogColor>1.0,1.0,1.0</fogColor>
            <skyColor>1.0,1.0,1.0</skyColor>
            <gravitationalMultiplier>130</gravitationalMultiplier>
            <orbitalDistance>215</orbitalDistance>
            <orbitalTheta>0</orbitalTheta>
            <orbitalPhi>0</orbitalPhi>
            <avgTemperature>196</avgTemperature>
            <rotationalPeriod>24000</rotationalPeriod>
            <atmosphereDensity>144</atmosphereDensity>
            <generateCraters>false</generateCraters>
            <generateVolcanos>false</generateVolcanos>
            <generateStructures>false</generateStructures>
            <generateGeodes>false</generateGeodes>
            <planet DIMID="157" name="Sol-156: 0">
                <isKnown>false</isKnown>
                <fogColor>1.0,1.0,1.0</fogColor>
                <skyColor>0.8,0.6467209,0.91572756</skyColor>
                <gravitationalMultiplier>55</gravitationalMultiplier>
                <orbitalDistance>144</orbitalDistance>
                <orbitalTheta>239</orbitalTheta>
                <orbitalPhi>-297</orbitalPhi>
                <avgTemperature>213</avgTemperature>
                <rotationalPeriod>144252</rotationalPeriod>
                <atmosphereDensity>13</atmosphereDensity>
                <generateCraters>true</generateCraters>
                <generateVolcanos>false</generateVolcanos>
                <generateStructures>false</generateStructures>
                <generateGeodes>false</generateGeodes>
                <craterFrequencyMultiplier>1.0</craterFrequencyMultiplier>
                <biomeIds>advancedrocketry:moon,advancedrocketry:moondark</biomeIds>
            </planet>
            <planet DIMID="158" name="Sol-156: 1">
                <isKnown>false</isKnown>
                <fogColor>1.0,1.0,1.0</fogColor>
                <skyColor>0.8,0.7578186,0.90465176</skyColor>
                <gravitationalMultiplier>79</gravitationalMultiplier>
                <orbitalDistance>127</orbitalDistance>
                <orbitalTheta>315</orbitalTheta>
                <orbitalPhi>-134</orbitalPhi>
                <avgTemperature>227</avgTemperature>
                <rotationalPeriod>48677</rotationalPeriod>
                <atmosphereDensity>26</atmosphereDensity>
                <generateCraters>true</generateCraters>
                <generateVolcanos>false</generateVolcanos>
                <generateStructures>false</generateStructures>
                <generateGeodes>false</generateGeodes>
                <craterFrequencyMultiplier>1.0</craterFrequencyMultiplier>
                <biomeIds>minecraft:mushroom_island_shore,traverse:rocky_plateau,minecraft:forest_hills,minecraft:birch_forest_hills,minecraft:mutated_redwood_taiga_hills</biomeIds>
            </planet>
            <planet DIMID="159" name="Sol-156: 2">
                <isKnown>false</isKnown>
                <fogColor>1.0,1.0,1.0</fogColor>
                <skyColor>0.8,0.53547126,0.8562288</skyColor>
                <gravitationalMultiplier>64</gravitationalMultiplier>
                <orbitalDistance>105</orbitalDistance>
                <orbitalTheta>232</orbitalTheta>
                <orbitalPhi>296</orbitalPhi>
                <avgTemperature>249</avgTemperature>
                <rotationalPeriod>91552</rotationalPeriod>
                <atmosphereDensity>36</atmosphereDensity>
                <generateCraters>true</generateCraters>
                <generateVolcanos>false</generateVolcanos>
                <generateStructures>false</generateStructures>
                <generateGeodes>false</generateGeodes>
                <craterFrequencyMultiplier>1.0</craterFrequencyMultiplier>
                <biomeIds>advancedrocketry:deepswamp,minecraft:extreme_hills,traverse:woodlands,minecraft:mushroom_island_shore,minecraft:jungle_hills</biomeIds>
            </planet>
        </planet>
    </star>
    <star blackHole="false" name="Stellaria" numGasGiants="0" numPlanets="0" size="1.0" temp="105" x="5" y="7">
        <planet DIMID="169" name="Sol-169">
            <isKnown>false</isKnown>
            <GasGiant>true</GasGiant>
            <gas>hydrogen</gas>
            <gas>oxygen</gas>
            <gas>nitrogen</gas>
            <fogColor>1.0,1.0,1.0</fogColor>
            <skyColor>1.0,1.0,1.0</skyColor>
            <gravitationalMultiplier>123</gravitationalMultiplier>
            <orbitalDistance>258</orbitalDistance>
            <orbitalTheta>0</orbitalTheta>
            <orbitalPhi>0</orbitalPhi>
            <avgTemperature>188</avgTemperature>
            <rotationalPeriod>24000</rotationalPeriod>
            <atmosphereDensity>156</atmosphereDensity>
            <generateCraters>false</generateCraters>
            <generateVolcanos>false</generateVolcanos>
            <generateStructures>false</generateStructures>
            <generateGeodes>false</generateGeodes>
            <planet DIMID="170" name="Sol-169: 0">
                <isKnown>false</isKnown>
                <fogColor>1.0,1.0,1.0</fogColor>
                <skyColor>0.8,0.8430972,0.9126677</skyColor>
                <gravitationalMultiplier>41</gravitationalMultiplier>
                <orbitalDistance>148</orbitalDistance>
                <orbitalTheta>122</orbitalTheta>
                <orbitalPhi>-178</orbitalPhi>
                <avgTemperature>220</avgTemperature>
                <rotationalPeriod>348224</rotationalPeriod>
                <atmosphereDensity>24</atmosphereDensity>
                <generateCraters>true</generateCraters>
                <generateVolcanos>false</generateVolcanos>
                <generateStructures>false</generateStructures>
                <generateGeodes>false</generateGeodes>
                <craterFrequencyMultiplier>1.0</craterFrequencyMultiplier>
                <biomeIds>advancedrocketry:moon,advancedrocketry:moondark</biomeIds>
            </planet>
            <planet DIMID="171" name="Sol-169: 1">
                <isKnown>false</isKnown>
                <fogColor>1.0,1.0,1.0</fogColor>
                <skyColor>0.8,0.81839216,0.9747943</skyColor>
                <gravitationalMultiplier>43</gravitationalMultiplier>
                <orbitalDistance>152</orbitalDistance>
                <orbitalTheta>251</orbitalTheta>
                <orbitalPhi>-74</orbitalPhi>
                <avgTemperature>217</avgTemperature>
                <rotationalPeriod>301860</rotationalPeriod>
                <atmosphereDensity>33</atmosphereDensity>
                <generateCraters>true</generateCraters>
                <generateVolcanos>false</generateVolcanos>
                <generateStructures>false</generateStructures>
                <generateGeodes>false</generateGeodes>
                <craterFrequencyMultiplier>1.0</craterFrequencyMultiplier>
                <biomeIds>minecraft:savanna,thaumcraft:eldritch,minecraft:jungle_edge,traverse:rocky_plains,minecraft:mushroom_island</biomeIds>
            </planet>
            <planet DIMID="172" name="Sol-169: 2">
                <isKnown>false</isKnown>
                <fogColor>1.0,1.0,1.0</fogColor>
                <skyColor>0.8,0.5187696,0.8822648</skyColor>
                <gravitationalMultiplier>40</gravitationalMultiplier>
                <orbitalDistance>154</orbitalDistance>
                <orbitalTheta>171</orbitalTheta>
                <orbitalPhi>-433</orbitalPhi>
                <avgTemperature>216</avgTemperature>
                <rotationalPeriod>375000</rotationalPeriod>
                <atmosphereDensity>34</atmosphereDensity>
                <generateCraters>true</generateCraters>
                <generateVolcanos>false</generateVolcanos>
                <generateStructures>false</generateStructures>
                <generateGeodes>false</generateGeodes>
                <craterFrequencyMultiplier>1.0</craterFrequencyMultiplier>
                <seaLevel>78</seaLevel>
                <biomeIds>thaumcraft:eerie,minecraft:mutated_forest,minecraft:desert_hills,minecraft:mutated_redwood_taiga_hills,traverse:rocky_plains</biomeIds>
            </planet>
            <planet DIMID="173" name="Sol-169: 3">
                <isKnown>false</isKnown>
                <fogColor>1.0,1.0,1.0</fogColor>
                <skyColor>0.8,0.9371251,0.8772948</skyColor>
                <gravitationalMultiplier>60</gravitationalMultiplier>
                <orbitalDistance>132</orbitalDistance>
                <orbitalTheta>252</orbitalTheta>
                <orbitalPhi>-63</orbitalPhi>
                <avgTemperature>233</avgTemperature>
                <rotationalPeriod>111111</rotationalPeriod>
                <atmosphereDensity>26</atmosphereDensity>
                <generateCraters>true</generateCraters>
                <generateVolcanos>false</generateVolcanos>
                <generateStructures>false</generateStructures>
                <generateGeodes>false</generateGeodes>
                <craterFrequencyMultiplier>1.0</craterFrequencyMultiplier>
                <biomeIds>traverse:mountainous_desert,traverse:mini_jungle,traverse:green_swamp,traverse:canyon,thaumcraft:eldritch</biomeIds>
            </planet>
        </planet>
        <planet DIMID="174" name="Sol-174">
            <isKnown>false</isKnown>
            <GasGiant>true</GasGiant>
            <gas>hydrogen</gas>
            <gas>oxygen</gas>
            <gas>nitrogen</gas>
            <fogColor>1.0,1.0,1.0</fogColor>
            <skyColor>1.0,1.0,1.0</skyColor>
            <gravitationalMultiplier>130</gravitationalMultiplier>
            <orbitalDistance>184</orbitalDistance>
            <orbitalTheta>0</orbitalTheta>
            <orbitalPhi>0</orbitalPhi>
            <avgTemperature>222</avgTemperature>
            <rotationalPeriod>24000</rotationalPeriod>
            <atmosphereDensity>182</atmosphereDensity>
            <generateCraters>false</generateCraters>
            <generateVolcanos>false</generateVolcanos>
            <generateStructures>false</generateStructures>
            <generateGeodes>false</generateGeodes>
            <planet DIMID="176" name="Sol-174: 1">
                <isKnown>false</isKnown>
                <fogColor>1.0,1.0,1.0</fogColor>
                <skyColor>0.8,0.6592025,0.81940913</skyColor>
                <gravitationalMultiplier>64</gravitationalMultiplier>
                <orbitalDistance>113</orbitalDistance>
                <orbitalTheta>104</orbitalTheta>
                <orbitalPhi>91</orbitalPhi>
                <avgTemperature>252</avgTemperature>
                <rotationalPeriod>91552</rotationalPeriod>
                <atmosphereDensity>19</atmosphereDensity>
                <generateCraters>true</generateCraters>
                <generateVolcanos>false</generateVolcanos>
                <generateStructures>false</generateStructures>
                <generateGeodes>false</generateGeodes>
                <craterFrequencyMultiplier>1.0</craterFrequencyMultiplier>
                <biomeIds>advancedrocketry:moon,advancedrocketry:moondark</biomeIds>
            </planet>
            <planet DIMID="177" name="Sol-174: 2">
                <isKnown>false</isKnown>
                <fogColor>1.0,1.0,1.0</fogColor>
                <skyColor>0.8,0.778373,0.83107543</skyColor>
                <gravitationalMultiplier>82</gravitationalMultiplier>
                <orbitalDistance>113</orbitalDistance>
                <orbitalTheta>158</orbitalTheta>
                <orbitalPhi>-166</orbitalPhi>
                <avgTemperature>252</avgTemperature>
                <rotationalPeriod>43528</rotationalPeriod>
                <atmosphereDensity>14</atmosphereDensity>
                <generateCraters>true</generateCraters>
                <generateVolcanos>false</generateVolcanos>
                <generateStructures>false</generateStructures>
                <generateGeodes>false</generateGeodes>
                <craterFrequencyMultiplier>1.0</craterFrequencyMultiplier>
                <biomeIds>advancedrocketry:moon,advancedrocketry:moondark</biomeIds>
            </planet>
            <planet DIMID="178" name="Sol-174: 3">
                <isKnown>false</isKnown>
                <fogColor>1.0,1.0,1.0</fogColor>
                <skyColor>0.8,0.75638723,0.96752</skyColor>
                <gravitationalMultiplier>48</gravitationalMultiplier>
                <orbitalDistance>165</orbitalDistance>
                <orbitalTheta>209</orbitalTheta>
                <orbitalPhi>-225</orbitalPhi>
                <avgTemperature>209</avgTemperature>
                <rotationalPeriod>217013</rotationalPeriod>
                <atmosphereDensity>21</atmosphereDensity>
                <generateCraters>true</generateCraters>
                <generateVolcanos>false</generateVolcanos>
                <generateStructures>false</generateStructures>
                <generateGeodes>false</generateGeodes>
                <craterFrequencyMultiplier>1.0</craterFrequencyMultiplier>
                <biomeIds>advancedrocketry:moon,advancedrocketry:moondark</biomeIds>
            </planet>
            <planet DIMID="175" name="Sol-174: 0">
                <isKnown>false</isKnown>
                <hasRings>true</hasRings>
                <ringColor>0.8,0.5533583,0.9189957</ringColor>
                <fogColor>1.0,1.0,1.0</fogColor>
                <skyColor>0.8,0.5533583,0.9189957</skyColor>
                <gravitationalMultiplier>84</gravitationalMultiplier>
                <orbitalDistance>158</orbitalDistance>
                <orbitalTheta>359</orbitalTheta>
                <orbitalPhi>-281</orbitalPhi>
                <avgTemperature>213</avgTemperature>
                <rotationalPeriod>40492</rotationalPeriod>
                <atmosphereDensity>16</atmosphereDensity>
                <generateCraters>true</generateCraters>
                <generateVolcanos>false</generateVolcanos>
                <generateStructures>false</generateStructures>
                <generateGeodes>false</generateGeodes>
                <craterFrequencyMultiplier>1.0</craterFrequencyMultiplier>
                <biomeIds>advancedrocketry:moon,advancedrocketry:moondark</biomeIds>
            </planet>
        </planet>
        <planet DIMID="146" name="Euclydes Prime">
            <isKnown>true</isKnown>
            <hasRings>true</hasRings>
            <ringColor>0.4,0.4,0.7</ringColor>
            <fogColor>1.0,1.0,1.0</fogColor>
            <skyColor>1.0,1.0,1.0</skyColor>
            <gravitationalMultiplier>104</gravitationalMultiplier>
            <orbitalDistance>90</orbitalDistance>
            <orbitalTheta>0</orbitalTheta>
            <orbitalPhi>0</orbitalPhi>
            <avgTemperature>318</avgTemperature>
            <rotationalPeriod>28000</rotationalPeriod>
            <atmosphereDensity>110</atmosphereDensity>
            <generateCraters>false</generateCraters>
            <generateVolcanos>false</generateVolcanos>
            <generateStructures>false</generateStructures>
            <generateGeodes>false</generateGeodes>
            <biomeIds>advancedrocketry:alien forest,advancedrocketry:oceanspires,minecraft:ocean</biomeIds>
            <oceanBlock>gregtech:fluid.blue_vitriol_water_solution</oceanBlock>
        </planet>
        <planet DIMID="179" name="Sol-179">
            <isKnown>false</isKnown>
            <GasGiant>true</GasGiant>
            <gas>hydrogen</gas>
            <gas>oxygen</gas>
            <gas>nitrogen</gas>
            <fogColor>1.0,1.0,1.0</fogColor>
            <skyColor>1.0,1.0,1.0</skyColor>
            <gravitationalMultiplier>120</gravitationalMultiplier>
            <orbitalDistance>227</orbitalDistance>
            <orbitalTheta>0</orbitalTheta>
            <orbitalPhi>0</orbitalPhi>
            <avgTemperature>200</avgTemperature>
            <rotationalPeriod>24000</rotationalPeriod>
            <atmosphereDensity>188</atmosphereDensity>
            <generateCraters>false</generateCraters>
            <generateVolcanos>false</generateVolcanos>
            <generateStructures>false</generateStructures>
            <generateGeodes>false</generateGeodes>
            <planet DIMID="180" name="Sol-179: 0">
                <isKnown>false</isKnown>
                <fogColor>1.0,1.0,1.0</fogColor>
                <skyColor>0.8,0.7705065,0.87926483</skyColor>
                <gravitationalMultiplier>58</gravitationalMultiplier>
                <orbitalDistance>125</orbitalDistance>
                <orbitalTheta>205</orbitalTheta>
                <orbitalPhi>-125</orbitalPhi>
                <avgTemperature>240</avgTemperature>
                <rotationalPeriod>116857</rotationalPeriod>
                <atmosphereDensity>30</atmosphereDensity>
                <generateCraters>true</generateCraters>
                <generateVolcanos>false</generateVolcanos>
                <generateStructures>false</generateStructures>
                <generateGeodes>false</generateGeodes>
                <craterFrequencyMultiplier>1.0</craterFrequencyMultiplier>
                <biomeIds>minecraft:mutated_mesa_rock,minecraft:roofed_forest,minecraft:mutated_roofed_forest,minecraft:deep_ocean,minecraft:mutated_savanna</biomeIds>
            </planet>
            <planet DIMID="181" name="Sol-179: 1">
                <isKnown>false</isKnown>
                <fogColor>1.0,1.0,1.0</fogColor>
                <skyColor>0.8,0.7952949,0.9827742</skyColor>
                <gravitationalMultiplier>66</gravitationalMultiplier>
                <orbitalDistance>182</orbitalDistance>
                <orbitalTheta>241</orbitalTheta>
                <orbitalPhi>181</orbitalPhi>
                <avgTemperature>199</avgTemperature>
                <rotationalPeriod>83479</rotationalPeriod>
                <atmosphereDensity>32</atmosphereDensity>
                <generateCraters>true</generateCraters>
                <generateVolcanos>false</generateVolcanos>
                <generateStructures>false</generateStructures>
                <generateGeodes>false</generateGeodes>
                <craterFrequencyMultiplier>1.0</craterFrequencyMultiplier>
                <biomeIds>advancedrocketry:stormland,minecraft:jungle_edge,minecraft:savanna_rock,traverse:meadow,advancedrocketry:alien forest</biomeIds>
            </planet>
        </planet>
        <planet DIMID="182" name="Sol-182">
            <isKnown>false</isKnown>
            <GasGiant>true</GasGiant>
            <gas>hydrogen</gas>
            <gas>oxygen</gas>
            <gas>nitrogen</gas>
            <fogColor>1.0,1.0,1.0</fogColor>
            <skyColor>1.0,1.0,1.0</skyColor>
            <gravitationalMultiplier>94</gravitationalMultiplier>
            <orbitalDistance>188</orbitalDistance>
            <orbitalTheta>0</orbitalTheta>
            <orbitalPhi>0</orbitalPhi>
            <avgTemperature>220</avgTemperature>
            <rotationalPeriod>24000</rotationalPeriod>
            <atmosphereDensity>199</atmosphereDensity>
            <generateCraters>false</generateCraters>
            <generateVolcanos>false</generateVolcanos>
            <generateStructures>false</generateStructures>
            <generateGeodes>false</generateGeodes>
        </planet>
        <planet DIMID="185" name="Sol-185">
            <isKnown>false</isKnown>
            <GasGiant>true</GasGiant>
            <gas>hydrogen</gas>
            <gas>oxygen</gas>
            <gas>nitrogen</gas>
            <fogColor>1.0,1.0,1.0</fogColor>
            <skyColor>1.0,1.0,1.0</skyColor>
            <gravitationalMultiplier>130</gravitationalMultiplier>
            <orbitalDistance>191</orbitalDistance>
            <orbitalTheta>0</orbitalTheta>
            <orbitalPhi>0</orbitalPhi>
            <avgTemperature>218</avgTemperature>
            <rotationalPeriod>24000</rotationalPeriod>
            <atmosphereDensity>186</atmosphereDensity>
            <generateCraters>false</generateCraters>
            <generateVolcanos>false</generateVolcanos>
            <generateStructures>false</generateStructures>
            <generateGeodes>false</generateGeodes>
            <planet DIMID="186" name="Sol-183: 2">
                <isKnown>false</isKnown>
                <fogColor>1.0,1.0,1.0</fogColor>
                <skyColor>0.8,0.923813,0.0</skyColor>
                <gravitationalMultiplier>71</gravitationalMultiplier>
                <orbitalDistance>111</orbitalDistance>
                <orbitalTheta>108</orbitalTheta>
                <orbitalPhi>120</orbitalPhi>
                <avgTemperature>575</avgTemperature>
                <rotationalPeriod>67055</rotationalPeriod>
                <atmosphereDensity>19</atmosphereDensity>
                <generateCraters>true</generateCraters>
                <generateVolcanos>true</generateVolcanos>
                <generateStructures>false</generateStructures>
                <generateGeodes>false</generateGeodes>
                <craterFrequencyMultiplier>1.0</craterFrequencyMultiplier>
                <volcanoFrequencyMultiplier>1.0</volcanoFrequencyMultiplier>
                <seaLevel>55</seaLevel>
                <biomeIds>advancedrocketry:moon,advancedrocketry:moondark</biomeIds>
                <oceanBlock>minecraft:lava</oceanBlock>
            </planet>
            <planet DIMID="187" name="Sol-183: 3">
                <isKnown>false</isKnown>
                <fogColor>1.0,1.0,1.0</fogColor>
                <skyColor>0.8,0.9012625,0.0</skyColor>
                <gravitationalMultiplier>58</gravitationalMultiplier>
                <orbitalDistance>110</orbitalDistance>
                <orbitalTheta>284</orbitalTheta>
                <orbitalPhi>-37</orbitalPhi>
                <avgTemperature>578</avgTemperature>
                <rotationalPeriod>123006</rotationalPeriod>
                <atmosphereDensity>20</atmosphereDensity>
                <generateCraters>true</generateCraters>
                <generateVolcanos>true</generateVolcanos>
                <generateStructures>false</generateStructures>
                <generateGeodes>false</generateGeodes>
                <craterFrequencyMultiplier>1.0</craterFrequencyMultiplier>
                <volcanoFrequencyMultiplier>1.0</volcanoFrequencyMultiplier>
                <seaLevel>67</seaLevel>
                <biomeIds>advancedrocketry:moon,advancedrocketry:moondark</biomeIds>
                <oceanBlock>minecraft:lava</oceanBlock>
            </planet>
            <planet DIMID="188" name="Sol-188">
                <isKnown>false</isKnown>
                <GasGiant>true</GasGiant>
                <gas>hydrogen</gas>
                <gas>oxygen</gas>
                <gas>nitrogen</gas>
                <fogColor>1.0,1.0,1.0</fogColor>
                <skyColor>1.0,1.0,1.0</skyColor>
                <gravitationalMultiplier>130</gravitationalMultiplier>
                <orbitalDistance>248</orbitalDistance>
                <orbitalTheta>0</orbitalTheta>
                <orbitalPhi>0</orbitalPhi>
                <avgTemperature>433</avgTemperature>
                <rotationalPeriod>24000</rotationalPeriod>
                <atmosphereDensity>178</atmosphereDensity>
                <generateCraters>false</generateCraters>
                <generateVolcanos>false</generateVolcanos>
                <generateStructures>false</generateStructures>
                <generateGeodes>false</generateGeodes>
                <planet DIMID="189" name="Sol-188: 0">
                    <isKnown>false</isKnown>
                    <fogColor>1.0,1.0,1.0</fogColor>
                    <skyColor>0.8,0.99175704,0.0</skyColor>
                    <gravitationalMultiplier>65</gravitationalMultiplier>
                    <orbitalDistance>141</orbitalDistance>
                    <orbitalTheta>159</orbitalTheta>
                    <orbitalPhi>19</orbitalPhi>
                    <avgTemperature>510</avgTemperature>
                    <rotationalPeriod>87391</rotationalPeriod>
                    <atmosphereDensity>22</atmosphereDensity>
                    <generateCraters>true</generateCraters>
                    <generateVolcanos>true</generateVolcanos>
                    <generateStructures>false</generateStructures>
                    <generateGeodes>false</generateGeodes>
                    <craterFrequencyMultiplier>1.0</craterFrequencyMultiplier>
                    <volcanoFrequencyMultiplier>1.0</volcanoFrequencyMultiplier>
                    <biomeIds>advancedrocketry:moon,advancedrocketry:moondark</biomeIds>
                    <oceanBlock>minecraft:lava</oceanBlock>
                </planet>
                <planet DIMID="190" name="Sol-188: 1">
                    <isKnown>false</isKnown>
                    <fogColor>1.0,1.0,1.0</fogColor>
                    <skyColor>0.8,0.61329395,0.0</skyColor>
                    <gravitationalMultiplier>57</gravitationalMultiplier>
                    <orbitalDistance>137</orbitalDistance>
                    <orbitalTheta>275</orbitalTheta>
                    <orbitalPhi>-437</orbitalPhi>
                    <avgTemperature>518</avgTemperature>
                    <rotationalPeriod>129594</rotationalPeriod>
                    <atmosphereDensity>13</atmosphereDensity>
                    <generateCraters>true</generateCraters>
                    <generateVolcanos>true</generateVolcanos>
                    <generateStructures>false</generateStructures>
                    <generateGeodes>false</generateGeodes>
                    <craterFrequencyMultiplier>1.0</craterFrequencyMultiplier>
                    <volcanoFrequencyMultiplier>1.0</volcanoFrequencyMultiplier>
                    <biomeIds>advancedrocketry:moon,advancedrocketry:moondark</biomeIds>
                    <oceanBlock>minecraft:lava</oceanBlock>
                </planet>
                <planet DIMID="191" name="Sol-188: 2">
                    <isKnown>false</isKnown>
                    <fogColor>1.0,1.0,1.0</fogColor>
                    <skyColor>0.8,0.7622585,0.0</skyColor>
                    <gravitationalMultiplier>80</gravitationalMultiplier>
                    <orbitalDistance>151</orbitalDistance>
                    <orbitalTheta>239</orbitalTheta>
                    <orbitalPhi>-99</orbitalPhi>
                    <avgTemperature>493</avgTemperature>
                    <rotationalPeriod>46875</rotationalPeriod>
                    <atmosphereDensity>18</atmosphereDensity>
                    <generateCraters>true</generateCraters>
                    <generateVolcanos>true</generateVolcanos>
                    <generateStructures>false</generateStructures>
                    <generateGeodes>false</generateGeodes>
                    <craterFrequencyMultiplier>1.0</craterFrequencyMultiplier>
                    <volcanoFrequencyMultiplier>1.0</volcanoFrequencyMultiplier>
                    <seaLevel>73</seaLevel>
                    <biomeIds>advancedrocketry:moon,advancedrocketry:moondark</biomeIds>
                    <oceanBlock>minecraft:lava</oceanBlock>
                </planet>
            </planet>
            <planet DIMID="189" name="Sol-188: 0">
                <isKnown>false</isKnown>
                <fogColor>1.0,1.0,1.0</fogColor>
                <skyColor>0.8,0.99175704,0.0</skyColor>
                <gravitationalMultiplier>65</gravitationalMultiplier>
                <orbitalDistance>141</orbitalDistance>
                <orbitalTheta>159</orbitalTheta>
                <orbitalPhi>19</orbitalPhi>
                <avgTemperature>510</avgTemperature>
                <rotationalPeriod>87391</rotationalPeriod>
                <atmosphereDensity>22</atmosphereDensity>
                <generateCraters>true</generateCraters>
                <generateVolcanos>true</generateVolcanos>
                <generateStructures>false</generateStructures>
                <generateGeodes>false</generateGeodes>
                <craterFrequencyMultiplier>1.0</craterFrequencyMultiplier>
                <volcanoFrequencyMultiplier>1.0</volcanoFrequencyMultiplier>
                <biomeIds>advancedrocketry:moon,advancedrocketry:moondark</biomeIds>
                <oceanBlock>minecraft:lava</oceanBlock>
            </planet>
        </planet>
    </star>
    <star blackHole="true" name="Xoal" numGasGiants="0" numPlanets="0" size="2.5" temp="150" x="0" y="-19">
        <planet DIMID="192" name="Sol-192">
            <isKnown>false</isKnown>
            <GasGiant>true</GasGiant>
            <gas>hydrogen</gas>
            <gas>oxygen</gas>
            <gas>nitrogen</gas>
            <fogColor>1.0,1.0,1.0</fogColor>
            <skyColor>1.0,1.0,1.0</skyColor>
            <gravitationalMultiplier>130</gravitationalMultiplier>
            <orbitalDistance>244</orbitalDistance>
            <orbitalTheta>0</orbitalTheta>
            <orbitalPhi>0</orbitalPhi>
            <avgTemperature>437</avgTemperature>
            <rotationalPeriod>24000</rotationalPeriod>
            <atmosphereDensity>197</atmosphereDensity>
            <generateCraters>false</generateCraters>
            <generateVolcanos>false</generateVolcanos>
            <generateStructures>false</generateStructures>
            <generateGeodes>false</generateGeodes>
            <planet DIMID="193" name="Sol-192: 0">
                <isKnown>false</isKnown>
                <fogColor>1.0,1.0,1.0</fogColor>
                <skyColor>0.8,0.96274364,0.0</skyColor>
                <gravitationalMultiplier>51</gravitationalMultiplier>
                <orbitalDistance>125</orbitalDistance>
                <orbitalTheta>319</orbitalTheta>
                <orbitalPhi>122</orbitalPhi>
                <avgTemperature>542</avgTemperature>
                <rotationalPeriod>180925</rotationalPeriod>
                <atmosphereDensity>19</atmosphereDensity>
                <generateCraters>true</generateCraters>
                <generateVolcanos>true</generateVolcanos>
                <generateStructures>false</generateStructures>
                <generateGeodes>false</generateGeodes>
                <craterFrequencyMultiplier>1.0</craterFrequencyMultiplier>
                <volcanoFrequencyMultiplier>1.0</volcanoFrequencyMultiplier>
                <biomeIds>advancedrocketry:moon,advancedrocketry:moondark</biomeIds>
                <oceanBlock>minecraft:lava</oceanBlock>
            </planet>
            <planet DIMID="194" name="Sol-192: 1">
                <isKnown>false</isKnown>
                <fogColor>1.0,1.0,1.0</fogColor>
                <skyColor>0.8,0.89480853,0.0</skyColor>
                <gravitationalMultiplier>72</gravitationalMultiplier>
                <orbitalDistance>146</orbitalDistance>
                <orbitalTheta>353</orbitalTheta>
                <orbitalPhi>-90</orbitalPhi>
                <avgTemperature>502</avgTemperature>
                <rotationalPeriod>64300</rotationalPeriod>
                <atmosphereDensity>22</atmosphereDensity>
                <generateCraters>true</generateCraters>
                <generateVolcanos>true</generateVolcanos>
                <generateStructures>false</generateStructures>
                <generateGeodes>false</generateGeodes>
                <craterFrequencyMultiplier>1.0</craterFrequencyMultiplier>
                <volcanoFrequencyMultiplier>1.0</volcanoFrequencyMultiplier>
                <seaLevel>72</seaLevel>
                <biomeIds>advancedrocketry:moon,advancedrocketry:moondark</biomeIds>
                <oceanBlock>minecraft:lava</oceanBlock>
            </planet>
            <planet DIMID="195" name="Sol-192: 2">
                <isKnown>false</isKnown>
                <fogColor>1.0,1.0,1.0</fogColor>
                <skyColor>0.8,0.53794277,0.024390459</skyColor>
                <gravitationalMultiplier>64</gravitationalMultiplier>
                <orbitalDistance>152</orbitalDistance>
                <orbitalTheta>46</orbitalTheta>
                <orbitalPhi>-75</orbitalPhi>
                <avgTemperature>492</avgTemperature>
                <rotationalPeriod>91552</rotationalPeriod>
                <atmosphereDensity>28</atmosphereDensity>
                <generateCraters>true</generateCraters>
                <generateVolcanos>true</generateVolcanos>
                <generateStructures>false</generateStructures>
                <generateGeodes>false</generateGeodes>
                <craterFrequencyMultiplier>1.0</craterFrequencyMultiplier>
                <volcanoFrequencyMultiplier>1.0</volcanoFrequencyMultiplier>
                <biomeIds>advancedrocketry:hotdryrock,advancedrocketry:volcanic,advancedrocketry:volcanicbarren</biomeIds>
                <oceanBlock>minecraft:lava</oceanBlock>
            </planet>
            <planet DIMID="196" name="Sol-192: 3">
                <isKnown>false</isKnown>
                <fogColor>1.0,1.0,1.0</fogColor>
                <skyColor>0.8,0.9440887,0.0</skyColor>
                <gravitationalMultiplier>48</gravitationalMultiplier>
                <orbitalDistance>132</orbitalDistance>
                <orbitalTheta>195</orbitalTheta>
                <orbitalPhi>-265</orbitalPhi>
                <avgTemperature>528</avgTemperature>
                <rotationalPeriod>217013</rotationalPeriod>
                <atmosphereDensity>18</atmosphereDensity>
                <generateCraters>true</generateCraters>
                <generateVolcanos>true</generateVolcanos>
                <generateStructures>false</generateStructures>
                <generateGeodes>false</generateGeodes>
                <craterFrequencyMultiplier>1.0</craterFrequencyMultiplier>
                <volcanoFrequencyMultiplier>1.0</volcanoFrequencyMultiplier>
                <biomeIds>advancedrocketry:moon,advancedrocketry:moondark</biomeIds>
                <oceanBlock>minecraft:lava</oceanBlock>
            </planet>
            <planet DIMID="197" name="Sol-192: 4">
                <isKnown>false</isKnown>
                <fogColor>1.0,1.0,1.0</fogColor>
                <skyColor>0.8,0.793043,0.0</skyColor>
                <gravitationalMultiplier>51</gravitationalMultiplier>
                <orbitalDistance>133</orbitalDistance>
                <orbitalTheta>33</orbitalTheta>
                <orbitalPhi>-216</orbitalPhi>
                <avgTemperature>526</avgTemperature>
                <rotationalPeriod>180925</rotationalPeriod>
                <atmosphereDensity>29</atmosphereDensity>
                <generateCraters>true</generateCraters>
                <generateVolcanos>true</generateVolcanos>
                <generateStructures>false</generateStructures>
                <generateGeodes>false</generateGeodes>
                <craterFrequencyMultiplier>1.0</craterFrequencyMultiplier>
                <volcanoFrequencyMultiplier>1.0</volcanoFrequencyMultiplier>
                <biomeIds>advancedrocketry:hotdryrock,advancedrocketry:volcanic,advancedrocketry:volcanicbarren</biomeIds>
                <oceanBlock>minecraft:lava</oceanBlock>
            </planet>
            <planet DIMID="198" name="Sol-192: 5">
                <isKnown>false</isKnown>
                <fogColor>1.0,1.0,1.0</fogColor>
                <skyColor>0.8,0.6746069,0.19747841</skyColor>
                <gravitationalMultiplier>72</gravitationalMultiplier>
                <orbitalDistance>191</orbitalDistance>
                <orbitalTheta>267</orbitalTheta>
                <orbitalPhi>-180</orbitalPhi>
                <avgTemperature>439</avgTemperature>
                <rotationalPeriod>64300</rotationalPeriod>
                <atmosphereDensity>13</atmosphereDensity>
                <generateCraters>true</generateCraters>
                <generateVolcanos>false</generateVolcanos>
                <generateStructures>false</generateStructures>
                <generateGeodes>false</generateGeodes>
                <craterFrequencyMultiplier>1.0</craterFrequencyMultiplier>
                <biomeIds>advancedrocketry:moon,advancedrocketry:moondark</biomeIds>
            </planet>
        </planet>
        <planet DIMID="199" name="Sol-199">
            <isKnown>false</isKnown>
            <GasGiant>true</GasGiant>
            <gas>hydrogen</gas>
            <gas>oxygen</gas>
            <gas>nitrogen</gas>
            <fogColor>1.0,1.0,1.0</fogColor>
            <skyColor>1.0,1.0,1.0</skyColor>
            <gravitationalMultiplier>127</gravitationalMultiplier>
            <orbitalDistance>191</orbitalDistance>
            <orbitalTheta>0</orbitalTheta>
            <orbitalPhi>0</orbitalPhi>
            <avgTemperature>493</avgTemperature>
            <rotationalPeriod>24000</rotationalPeriod>
            <atmosphereDensity>144</atmosphereDensity>
            <generateCraters>false</generateCraters>
            <generateVolcanos>false</generateVolcanos>
            <generateStructures>false</generateStructures>
            <generateGeodes>false</generateGeodes>
            <planet DIMID="200" name="Sol-199: 0">
                <isKnown>false</isKnown>
                <fogColor>1.0,1.0,1.0</fogColor>
                <skyColor>0.8,0.6968031,0.18132281</skyColor>
                <gravitationalMultiplier>50</gravitationalMultiplier>
                <orbitalDistance>182</orbitalDistance>
                <orbitalTheta>75</orbitalTheta>
                <orbitalPhi>56</orbitalPhi>
                <avgTemperature>449</avgTemperature>
                <rotationalPeriod>192000</rotationalPeriod>
                <atmosphereDensity>21</atmosphereDensity>
                <generateCraters>true</generateCraters>
                <generateVolcanos>false</generateVolcanos>
                <generateStructures>false</generateStructures>
                <generateGeodes>false</generateGeodes>
                <craterFrequencyMultiplier>1.0</craterFrequencyMultiplier>
                <seaLevel>67</seaLevel>
                <biomeIds>advancedrocketry:moon,advancedrocketry:moondark</biomeIds>
            </planet>
            <planet DIMID="201" name="Sol-199: 1">
                <isKnown>false</isKnown>
                <fogColor>1.0,1.0,1.0</fogColor>
                <skyColor>0.8,0.89356625,0.0</skyColor>
                <gravitationalMultiplier>58</gravitationalMultiplier>
                <orbitalDistance>139</orbitalDistance>
                <orbitalTheta>246</orbitalTheta>
                <orbitalPhi>-334</orbitalPhi>
                <avgTemperature>514</avgTemperature>
                <rotationalPeriod>123006</rotationalPeriod>
                <atmosphereDensity>13</atmosphereDensity>
                <generateCraters>true</generateCraters>
                <generateVolcanos>true</generateVolcanos>
                <generateStructures>false</generateStructures>
                <generateGeodes>false</generateGeodes>
                <craterFrequencyMultiplier>1.0</craterFrequencyMultiplier>
                <volcanoFrequencyMultiplier>1.0</volcanoFrequencyMultiplier>
                <seaLevel>73</seaLevel>
                <biomeIds>advancedrocketry:moon,advancedrocketry:moondark</biomeIds>
                <oceanBlock>minecraft:lava</oceanBlock>
            </planet>
        </planet>
        <planet DIMID="202" name="Sol-202">
            <isKnown>false</isKnown>
            <GasGiant>true</GasGiant>
            <gas>hydrogen</gas>
            <gas>oxygen</gas>
            <gas>nitrogen</gas>
            <fogColor>1.0,1.0,1.0</fogColor>
            <skyColor>1.0,1.0,1.0</skyColor>
            <gravitationalMultiplier>130</gravitationalMultiplier>
            <orbitalDistance>257</orbitalDistance>
            <orbitalTheta>0</orbitalTheta>
            <orbitalPhi>0</orbitalPhi>
            <avgTemperature>425</avgTemperature>
            <rotationalPeriod>24000</rotationalPeriod>
            <atmosphereDensity>158</atmosphereDensity>
            <generateCraters>false</generateCraters>
            <generateVolcanos>false</generateVolcanos>
            <generateStructures>false</generateStructures>
            <generateGeodes>false</generateGeodes>
            <planet DIMID="208" name="Sol-202: 5">
                <isKnown>false</isKnown>
                <fogColor>1.0,1.0,1.0</fogColor>
                <skyColor>0.8,0.98202324,0.1695866</skyColor>
                <gravitationalMultiplier>70</gravitationalMultiplier>
                <orbitalDistance>186</orbitalDistance>
                <orbitalTheta>114</orbitalTheta>
                <orbitalPhi>-38</orbitalPhi>
                <avgTemperature>444</avgTemperature>
                <rotationalPeriod>69970</rotationalPeriod>
                <atmosphereDensity>32</atmosphereDensity>
                <generateCraters>true</generateCraters>
                <generateVolcanos>false</generateVolcanos>
                <generateStructures>false</generateStructures>
                <generateGeodes>false</generateGeodes>
                <craterFrequencyMultiplier>1.0</craterFrequencyMultiplier>
                <biomeIds>minecraft:mutated_mesa,minecraft:ocean,advancedrocketry:marsh,minecraft:jungle_edge,minecraft:mutated_jungle</biomeIds>
            </planet>
            <planet DIMID="203" name="Sol-202: 0">
                <isKnown>false</isKnown>
                <fogColor>1.0,1.0,1.0</fogColor>
                <skyColor>0.8,0.91544855,0.0</skyColor>
                <gravitationalMultiplier>48</gravitationalMultiplier>
                <orbitalDistance>110</orbitalDistance>
                <orbitalTheta>351</orbitalTheta>
                <orbitalPhi>-128</orbitalPhi>
                <avgTemperature>578</avgTemperature>
                <rotationalPeriod>217013</rotationalPeriod>
                <atmosphereDensity>27</atmosphereDensity>
                <generateCraters>true</generateCraters>
                <generateVolcanos>true</generateVolcanos>
                <generateStructures>false</generateStructures>
                <generateGeodes>false</generateGeodes>
                <craterFrequencyMultiplier>1.0</craterFrequencyMultiplier>
                <volcanoFrequencyMultiplier>1.0</volcanoFrequencyMultiplier>
                <biomeIds>advancedrocketry:hotdryrock,advancedrocketry:volcanic,advancedrocketry:volcanicbarren</biomeIds>
                <oceanBlock>minecraft:lava</oceanBlock>
            </planet>
            <planet DIMID="204" name="Sol-202: 1">
                <isKnown>false</isKnown>
                <fogColor>1.0,1.0,1.0</fogColor>
                <skyColor>0.8,0.9429615,0.0</skyColor>
                <gravitationalMultiplier>85</gravitationalMultiplier>
                <orbitalDistance>137</orbitalDistance>
                <orbitalTheta>338</orbitalTheta>
                <orbitalPhi>52</orbitalPhi>
                <avgTemperature>518</avgTemperature>
                <rotationalPeriod>39079</rotationalPeriod>
                <atmosphereDensity>27</atmosphereDensity>
                <generateCraters>true</generateCraters>
                <generateVolcanos>true</generateVolcanos>
                <generateStructures>false</generateStructures>
                <generateGeodes>false</generateGeodes>
                <craterFrequencyMultiplier>1.0</craterFrequencyMultiplier>
                <volcanoFrequencyMultiplier>1.0</volcanoFrequencyMultiplier>
                <biomeIds>advancedrocketry:hotdryrock,advancedrocketry:volcanic,advancedrocketry:volcanicbarren</biomeIds>
                <oceanBlock>minecraft:lava</oceanBlock>
            </planet>
            <planet DIMID="205" name="Sol-202: 2">
                <isKnown>false</isKnown>
                <fogColor>1.0,1.0,1.0</fogColor>
                <skyColor>0.8,0.7309364,0.0</skyColor>
                <gravitationalMultiplier>62</gravitationalMultiplier>
                <orbitalDistance>110</orbitalDistance>
                <orbitalTheta>287</orbitalTheta>
                <orbitalPhi>-122</orbitalPhi>
                <avgTemperature>578</avgTemperature>
                <rotationalPeriod>100701</rotationalPeriod>
                <atmosphereDensity>28</atmosphereDensity>
                <generateCraters>true</generateCraters>
                <generateVolcanos>true</generateVolcanos>
                <generateStructures>false</generateStructures>
                <generateGeodes>false</generateGeodes>
                <craterFrequencyMultiplier>1.0</craterFrequencyMultiplier>
                <volcanoFrequencyMultiplier>1.0</volcanoFrequencyMultiplier>
                <seaLevel>64</seaLevel>
                <biomeIds>advancedrocketry:hotdryrock,advancedrocketry:volcanic,advancedrocketry:volcanicbarren</biomeIds>
                <oceanBlock>minecraft:lava</oceanBlock>
            </planet>
            <planet DIMID="206" name="Sol-202: 3">
                <isKnown>false</isKnown>
                <fogColor>1.0,1.0,1.0</fogColor>
                <skyColor>0.8,0.9987999,0.10412198</skyColor>
                <gravitationalMultiplier>50</gravitationalMultiplier>
                <orbitalDistance>172</orbitalDistance>
                <orbitalTheta>148</orbitalTheta>
                <orbitalPhi>-176</orbitalPhi>
                <avgTemperature>462</avgTemperature>
                <rotationalPeriod>192000</rotationalPeriod>
                <atmosphereDensity>27</atmosphereDensity>
                <generateCraters>true</generateCraters>
                <generateVolcanos>true</generateVolcanos>
                <generateStructures>false</generateStructures>
                <generateGeodes>false</generateGeodes>
                <craterFrequencyMultiplier>1.0</craterFrequencyMultiplier>
                <volcanoFrequencyMultiplier>1.0</volcanoFrequencyMultiplier>
                <biomeIds>advancedrocketry:hotdryrock,advancedrocketry:volcanic,advancedrocketry:volcanicbarren</biomeIds>
                <oceanBlock>minecraft:lava</oceanBlock>
            </planet>
            <planet DIMID="207" name="Sol-202: 4">
                <isKnown>false</isKnown>
                <fogColor>1.0,1.0,1.0</fogColor>
                <skyColor>0.8,0.83061683,0.0</skyColor>
                <gravitationalMultiplier>77</gravitationalMultiplier>
                <orbitalDistance>129</orbitalDistance>
                <orbitalTheta>212</orbitalTheta>
                <orbitalPhi>-209</orbitalPhi>
                <avgTemperature>534</avgTemperature>
                <rotationalPeriod>52570</rotationalPeriod>
                <atmosphereDensity>23</atmosphereDensity>
                <generateCraters>true</generateCraters>
                <generateVolcanos>true</generateVolcanos>
                <generateStructures>false</generateStructures>
                <generateGeodes>false</generateGeodes>
                <craterFrequencyMultiplier>1.0</craterFrequencyMultiplier>
                <volcanoFrequencyMultiplier>1.0</volcanoFrequencyMultiplier>
                <biomeIds>advancedrocketry:moon,advancedrocketry:moondark</biomeIds>
                <oceanBlock>minecraft:lava</oceanBlock>
            </planet>
        </planet>
        <planet DIMID="209" name="Sol-209">
            <isKnown>false</isKnown>
            <GasGiant>true</GasGiant>
            <gas>hydrogen</gas>
            <gas>oxygen</gas>
            <gas>nitrogen</gas>
            <fogColor>1.0,1.0,1.0</fogColor>
            <skyColor>1.0,1.0,1.0</skyColor>
            <gravitationalMultiplier>124</gravitationalMultiplier>
            <orbitalDistance>195</orbitalDistance>
            <orbitalTheta>0</orbitalTheta>
            <orbitalPhi>0</orbitalPhi>
            <avgTemperature>488</avgTemperature>
            <rotationalPeriod>24000</rotationalPeriod>
            <atmosphereDensity>144</atmosphereDensity>
            <generateCraters>false</generateCraters>
            <generateVolcanos>false</generateVolcanos>
            <generateStructures>false</generateStructures>
            <generateGeodes>false</generateGeodes>
            <planet DIMID="210" name="Sol-209: 0">
                <isKnown>false</isKnown>
                <fogColor>1.0,1.0,1.0</fogColor>
                <skyColor>0.8,0.8752103,0.0634619</skyColor>
                <gravitationalMultiplier>86</gravitationalMultiplier>
                <orbitalDistance>158</orbitalDistance>
                <orbitalTheta>129</orbitalTheta>
                <orbitalPhi>-53</orbitalPhi>
                <avgTemperature>482</avgTemperature>
                <rotationalPeriod>37732</rotationalPeriod>
                <atmosphereDensity>35</atmosphereDensity>
                <generateCraters>true</generateCraters>
                <generateVolcanos>true</generateVolcanos>
                <generateStructures>false</generateStructures>
                <generateGeodes>false</generateGeodes>
                <craterFrequencyMultiplier>1.0</craterFrequencyMultiplier>
                <volcanoFrequencyMultiplier>1.0</volcanoFrequencyMultiplier>
                <biomeIds>advancedrocketry:hotdryrock,advancedrocketry:volcanic,advancedrocketry:volcanicbarren</biomeIds>
                <oceanBlock>minecraft:lava</oceanBlock>
            </planet>
            <planet DIMID="211" name="Sol-209: 1">
                <isKnown>false</isKnown>
                <fogColor>1.0,1.0,1.0</fogColor>
                <skyColor>0.8,0.7238122,0.0</skyColor>
                <gravitationalMultiplier>76</gravitationalMultiplier>
                <orbitalDistance>111</orbitalDistance>
                <orbitalTheta>78</orbitalTheta>
                <orbitalPhi>-91</orbitalPhi>
                <avgTemperature>575</avgTemperature>
                <rotationalPeriod>54672</rotationalPeriod>
                <atmosphereDensity>17</atmosphereDensity>
                <generateCraters>true</generateCraters>
                <generateVolcanos>true</generateVolcanos>
                <generateStructures>false</generateStructures>
                <generateGeodes>false</generateGeodes>
                <craterFrequencyMultiplier>1.0</craterFrequencyMultiplier>
                <volcanoFrequencyMultiplier>1.0</volcanoFrequencyMultiplier>
                <biomeIds>advancedrocketry:moon,advancedrocketry:moondark</biomeIds>
                <oceanBlock>minecraft:lava</oceanBlock>
            </planet>
            <planet DIMID="212" name="Sol-209: 2">
                <isKnown>false</isKnown>
                <fogColor>1.0,1.0,1.0</fogColor>
                <skyColor>0.8,0.56036174,0.0</skyColor>
                <gravitationalMultiplier>86</gravitationalMultiplier>
                <orbitalDistance>112</orbitalDistance>
                <orbitalTheta>77</orbitalTheta>
                <orbitalPhi>-195</orbitalPhi>
                <avgTemperature>573</avgTemperature>
                <rotationalPeriod>37732</rotationalPeriod>
                <atmosphereDensity>29</atmosphereDensity>
                <generateCraters>true</generateCraters>
                <generateVolcanos>true</generateVolcanos>
                <generateStructures>false</generateStructures>
                <generateGeodes>false</generateGeodes>
                <craterFrequencyMultiplier>1.0</craterFrequencyMultiplier>
                <volcanoFrequencyMultiplier>1.0</volcanoFrequencyMultiplier>
                <biomeIds>advancedrocketry:hotdryrock,advancedrocketry:volcanic,advancedrocketry:volcanicbarren</biomeIds>
                <oceanBlock>minecraft:lava</oceanBlock>
            </planet>
            <planet DIMID="213" name="Sol-209: 3">
                <isKnown>false</isKnown>
                <fogColor>1.0,1.0,1.0</fogColor>
                <skyColor>0.8,0.94019246,0.24474645</skyColor>
                <gravitationalMultiplier>58</gravitationalMultiplier>
                <orbitalDistance>192</orbitalDistance>
                <orbitalTheta>52</orbitalTheta>
                <orbitalPhi>-55</orbitalPhi>
                <avgTemperature>437</avgTemperature>
                <rotationalPeriod>123006</rotationalPeriod>
                <atmosphereDensity>20</atmosphereDensity>
                <generateCraters>true</generateCraters>
                <generateVolcanos>false</generateVolcanos>
                <generateStructures>false</generateStructures>
                <generateGeodes>false</generateGeodes>
                <craterFrequencyMultiplier>1.0</craterFrequencyMultiplier>
                <biomeIds>advancedrocketry:moon,advancedrocketry:moondark</biomeIds>
            </planet>
            <planet DIMID="214" name="Sol-209: 4">
                <isKnown>false</isKnown>
                <fogColor>1.0,1.0,1.0</fogColor>
                <skyColor>0.8,0.7400013,0.06318581</skyColor>
                <gravitationalMultiplier>41</gravitationalMultiplier>
                <orbitalDistance>153</orbitalDistance>
                <orbitalTheta>267</orbitalTheta>
                <orbitalPhi>-154</orbitalPhi>
                <avgTemperature>490</avgTemperature>
                <rotationalPeriod>348224</rotationalPeriod>
                <atmosphereDensity>20</atmosphereDensity>
                <generateCraters>true</generateCraters>
                <generateVolcanos>true</generateVolcanos>
                <generateStructures>false</generateStructures>
                <generateGeodes>false</generateGeodes>
                <craterFrequencyMultiplier>1.0</craterFrequencyMultiplier>
                <volcanoFrequencyMultiplier>1.0</volcanoFrequencyMultiplier>
                <seaLevel>75</seaLevel>
                <biomeIds>advancedrocketry:moon,advancedrocketry:moondark</biomeIds>
                <oceanBlock>minecraft:lava</oceanBlock>
            </planet>
            <planet DIMID="215" name="Sol-209: 5">
                <isKnown>false</isKnown>
                <fogColor>1.0,1.0,1.0</fogColor>
                <skyColor>0.8,0.99181724,0.0</skyColor>
                <gravitationalMultiplier>73</gravitationalMultiplier>
                <orbitalDistance>113</orbitalDistance>
                <orbitalTheta>152</orbitalTheta>
                <orbitalPhi>-58</orbitalPhi>
                <avgTemperature>570</avgTemperature>
                <rotationalPeriod>61693</rotationalPeriod>
                <atmosphereDensity>21</atmosphereDensity>
                <generateCraters>true</generateCraters>
                <generateVolcanos>true</generateVolcanos>
                <generateStructures>false</generateStructures>
                <generateGeodes>false</generateGeodes>
                <craterFrequencyMultiplier>1.0</craterFrequencyMultiplier>
                <volcanoFrequencyMultiplier>1.0</volcanoFrequencyMultiplier>
                <biomeIds>advancedrocketry:moon,advancedrocketry:moondark</biomeIds>
                <oceanBlock>minecraft:lava</oceanBlock>
            </planet>
        </planet>
        <planet DIMID="147" name="Aurellia">
            <isKnown>true</isKnown>
            <fogColor>1.0,1.0,1.0</fogColor>
            <skyColor>1.0,1.0,1.0</skyColor>
            <gravitationalMultiplier>200</gravitationalMultiplier>
            <orbitalDistance>30</orbitalDistance>
            <orbitalTheta>0</orbitalTheta>
            <orbitalPhi>30</orbitalPhi>
            <avgTemperature>1107</avgTemperature>
            <rotationalPeriod>2400</rotationalPeriod>
            <atmosphereDensity>80</atmosphereDensity>
            <generateCraters>false</generateCraters>
            <generateVolcanos>false</generateVolcanos>
            <generateStructures>false</generateStructures>
            <generateGeodes>false</generateGeodes>
            <biomeIds>advancedrocketry:hotdryrock,advancedrocketry:crystalchasms,minecraft:ocean</biomeIds>
            <oceanBlock>tconstruct:molten_obsidian</oceanBlock>
        </planet>
        <planet DIMID="216" name="Sol-216">
            <isKnown>false</isKnown>
            <GasGiant>true</GasGiant>
            <gas>hydrogen</gas>
            <gas>oxygen</gas>
            <gas>nitrogen</gas>
            <fogColor>1.0,1.0,1.0</fogColor>
            <skyColor>1.0,1.0,1.0</skyColor>
            <gravitationalMultiplier>130</gravitationalMultiplier>
            <orbitalDistance>222</orbitalDistance>
            <orbitalTheta>0</orbitalTheta>
            <orbitalPhi>0</orbitalPhi>
            <avgTemperature>458</avgTemperature>
            <rotationalPeriod>24000</rotationalPeriod>
            <atmosphereDensity>133</atmosphereDensity>
            <generateCraters>false</generateCraters>
            <generateVolcanos>false</generateVolcanos>
            <generateStructures>false</generateStructures>
            <generateGeodes>false</generateGeodes>
        </planet>
        <planet DIMID="183" name="Sol-183">
            <isKnown>false</isKnown>
            <GasGiant>true</GasGiant>
            <gas>hydrogen</gas>
            <gas>oxygen</gas>
            <gas>nitrogen</gas>
            <fogColor>1.0,1.0,1.0</fogColor>
            <skyColor>1.0,1.0,1.0</skyColor>
            <gravitationalMultiplier>117</gravitationalMultiplier>
            <orbitalDistance>257</orbitalDistance>
            <orbitalTheta>0</orbitalTheta>
            <orbitalPhi>0</orbitalPhi>
            <avgTemperature>425</avgTemperature>
            <rotationalPeriod>24000</rotationalPeriod>
            <atmosphereDensity>192</atmosphereDensity>
            <generateCraters>false</generateCraters>
            <generateVolcanos>false</generateVolcanos>
            <generateStructures>false</generateStructures>
            <generateGeodes>false</generateGeodes>
            <planet DIMID="184" name="Sol-183: 0">
                <isKnown>false</isKnown>
                <fogColor>1.0,1.0,1.0</fogColor>
                <skyColor>0.8,0.8373945,0.1269651</skyColor>
                <gravitationalMultiplier>46</gravitationalMultiplier>
                <orbitalDistance>171</orbitalDistance>
                <orbitalTheta>301</orbitalTheta>
                <orbitalPhi>-238</orbitalPhi>
                <avgTemperature>464</avgTemperature>
                <rotationalPeriod>246568</rotationalPeriod>
                <atmosphereDensity>22</atmosphereDensity>
                <generateCraters>true</generateCraters>
                <generateVolcanos>true</generateVolcanos>
                <generateStructures>false</generateStructures>
                <generateGeodes>false</generateGeodes>
                <craterFrequencyMultiplier>1.0</craterFrequencyMultiplier>
                <volcanoFrequencyMultiplier>1.0</volcanoFrequencyMultiplier>
                <seaLevel>76</seaLevel>
                <biomeIds>advancedrocketry:moon,advancedrocketry:moondark</biomeIds>
                <oceanBlock>minecraft:lava</oceanBlock>
            </planet>
            <planet DIMID="185" name="Sol-183: 1">
                <isKnown>false</isKnown>
                <fogColor>1.0,1.0,1.0</fogColor>
                <skyColor>0.8,0.8354308,0.0</skyColor>
                <gravitationalMultiplier>34</gravitationalMultiplier>
                <orbitalDistance>109</orbitalDistance>
                <orbitalTheta>284</orbitalTheta>
                <orbitalPhi>-434</orbitalPhi>
                <avgTemperature>581</avgTemperature>
                <rotationalPeriod>610624</rotationalPeriod>
                <atmosphereDensity>15</atmosphereDensity>
                <generateCraters>true</generateCraters>
                <generateVolcanos>true</generateVolcanos>
                <generateStructures>false</generateStructures>
                <generateGeodes>false</generateGeodes>
                <craterFrequencyMultiplier>1.0</craterFrequencyMultiplier>
                <volcanoFrequencyMultiplier>1.0</volcanoFrequencyMultiplier>
                <biomeIds>advancedrocketry:moon,advancedrocketry:moondark</biomeIds>
                <oceanBlock>minecraft:lava</oceanBlock>
            </planet>
            <planet DIMID="186" name="Sol-183: 2">
                <isKnown>false</isKnown>
                <fogColor>1.0,1.0,1.0</fogColor>
                <skyColor>0.8,0.923813,0.0</skyColor>
                <gravitationalMultiplier>71</gravitationalMultiplier>
                <orbitalDistance>111</orbitalDistance>
                <orbitalTheta>108</orbitalTheta>
                <orbitalPhi>120</orbitalPhi>
                <avgTemperature>575</avgTemperature>
                <rotationalPeriod>67055</rotationalPeriod>
                <atmosphereDensity>19</atmosphereDensity>
                <generateCraters>true</generateCraters>
                <generateVolcanos>true</generateVolcanos>
                <generateStructures>false</generateStructures>
                <generateGeodes>false</generateGeodes>
                <craterFrequencyMultiplier>1.0</craterFrequencyMultiplier>
                <volcanoFrequencyMultiplier>1.0</volcanoFrequencyMultiplier>
                <seaLevel>55</seaLevel>
                <biomeIds>advancedrocketry:moon,advancedrocketry:moondark</biomeIds>
                <oceanBlock>minecraft:lava</oceanBlock>
            </planet>
            <planet DIMID="187" name="Sol-183: 3">
                <isKnown>false</isKnown>
                <fogColor>1.0,1.0,1.0</fogColor>
                <skyColor>0.8,0.9012625,0.0</skyColor>
                <gravitationalMultiplier>58</gravitationalMultiplier>
                <orbitalDistance>110</orbitalDistance>
                <orbitalTheta>284</orbitalTheta>
                <orbitalPhi>-37</orbitalPhi>
                <avgTemperature>578</avgTemperature>
                <rotationalPeriod>123006</rotationalPeriod>
                <atmosphereDensity>20</atmosphereDensity>
                <generateCraters>true</generateCraters>
                <generateVolcanos>true</generateVolcanos>
                <generateStructures>false</generateStructures>
                <generateGeodes>false</generateGeodes>
                <craterFrequencyMultiplier>1.0</craterFrequencyMultiplier>
                <volcanoFrequencyMultiplier>1.0</volcanoFrequencyMultiplier>
                <seaLevel>67</seaLevel>
                <biomeIds>advancedrocketry:moon,advancedrocketry:moondark</biomeIds>
                <oceanBlock>minecraft:lava</oceanBlock>
            </planet>
        </planet>
        <planet DIMID="188" name="Sol-188">
            <isKnown>false</isKnown>
            <GasGiant>true</GasGiant>
            <gas>hydrogen</gas>
            <gas>oxygen</gas>
            <gas>nitrogen</gas>
            <fogColor>1.0,1.0,1.0</fogColor>
            <skyColor>1.0,1.0,1.0</skyColor>
            <gravitationalMultiplier>130</gravitationalMultiplier>
            <orbitalDistance>248</orbitalDistance>
            <orbitalTheta>0</orbitalTheta>
            <orbitalPhi>0</orbitalPhi>
            <avgTemperature>433</avgTemperature>
            <rotationalPeriod>24000</rotationalPeriod>
            <atmosphereDensity>178</atmosphereDensity>
            <generateCraters>false</generateCraters>
            <generateVolcanos>false</generateVolcanos>
            <generateStructures>false</generateStructures>
            <generateGeodes>false</generateGeodes>
            <planet DIMID="189" name="Sol-188: 0">
                <isKnown>false</isKnown>
                <fogColor>1.0,1.0,1.0</fogColor>
                <skyColor>0.8,0.99175704,0.0</skyColor>
                <gravitationalMultiplier>65</gravitationalMultiplier>
                <orbitalDistance>141</orbitalDistance>
                <orbitalTheta>159</orbitalTheta>
                <orbitalPhi>19</orbitalPhi>
                <avgTemperature>510</avgTemperature>
                <rotationalPeriod>87391</rotationalPeriod>
                <atmosphereDensity>22</atmosphereDensity>
                <generateCraters>true</generateCraters>
                <generateVolcanos>true</generateVolcanos>
                <generateStructures>false</generateStructures>
                <generateGeodes>false</generateGeodes>
                <craterFrequencyMultiplier>1.0</craterFrequencyMultiplier>
                <volcanoFrequencyMultiplier>1.0</volcanoFrequencyMultiplier>
                <biomeIds>advancedrocketry:moon,advancedrocketry:moondark</biomeIds>
                <oceanBlock>minecraft:lava</oceanBlock>
            </planet>
            <planet DIMID="190" name="Sol-188: 1">
                <isKnown>false</isKnown>
                <fogColor>1.0,1.0,1.0</fogColor>
                <skyColor>0.8,0.61329395,0.0</skyColor>
                <gravitationalMultiplier>57</gravitationalMultiplier>
                <orbitalDistance>137</orbitalDistance>
                <orbitalTheta>275</orbitalTheta>
                <orbitalPhi>-437</orbitalPhi>
                <avgTemperature>518</avgTemperature>
                <rotationalPeriod>129594</rotationalPeriod>
                <atmosphereDensity>13</atmosphereDensity>
                <generateCraters>true</generateCraters>
                <generateVolcanos>true</generateVolcanos>
                <generateStructures>false</generateStructures>
                <generateGeodes>false</generateGeodes>
                <craterFrequencyMultiplier>1.0</craterFrequencyMultiplier>
                <volcanoFrequencyMultiplier>1.0</volcanoFrequencyMultiplier>
                <biomeIds>advancedrocketry:moon,advancedrocketry:moondark</biomeIds>
                <oceanBlock>minecraft:lava</oceanBlock>
            </planet>
            <planet DIMID="191" name="Sol-188: 2">
                <isKnown>false</isKnown>
                <fogColor>1.0,1.0,1.0</fogColor>
                <skyColor>0.8,0.7622585,0.0</skyColor>
                <gravitationalMultiplier>80</gravitationalMultiplier>
                <orbitalDistance>151</orbitalDistance>
                <orbitalTheta>239</orbitalTheta>
                <orbitalPhi>-99</orbitalPhi>
                <avgTemperature>493</avgTemperature>
                <rotationalPeriod>46875</rotationalPeriod>
                <atmosphereDensity>18</atmosphereDensity>
                <generateCraters>true</generateCraters>
                <generateVolcanos>true</generateVolcanos>
                <generateStructures>false</generateStructures>
                <generateGeodes>false</generateGeodes>
                <craterFrequencyMultiplier>1.0</craterFrequencyMultiplier>
                <volcanoFrequencyMultiplier>1.0</volcanoFrequencyMultiplier>
                <seaLevel>73</seaLevel>
                <biomeIds>advancedrocketry:moon,advancedrocketry:moondark</biomeIds>
                <oceanBlock>minecraft:lava</oceanBlock>
            </planet>
        </planet>
    </star>
</galaxy>
