{IsEmpty:0b,InventoryHolder:{Zcoord:-1446,cosmeticarmor:[],PlayerName:[],Ycoord:15,Xcoord:-3046,bauble:[],Timestamp:[],vanilla:[{Slot:0b,ForgeCaps:{"astralsorcery:cap_item_amulet_holder":{}},id:"advancedrocketry:jackhammer",Count:1b,tag:{ench:[{lvl:1,id:70},{lvl:3,id:34},{lvl:5,id:32},{lvl:1,id:24}],RepairCost:15,pickletweaks:{BlocksBroken:24553}},Damage:317s},{Slot:1b,id:"harvestcraft:candledeco1",Count:20b,Damage:0s},{Slot:2b,id:"minecraft:cobblestone",Count:64b,Damage:0s},{Slot:3b,id:"minecraft:leather",Count:2b,Damage:0s},{Slot:4b,id:"minecraft:chest",Count:4b,Damage:0s},{Slot:5b,id:"plants2:crystal_torch",Count:16b,Damage:0s},{Slot:6b,ForgeCaps:{"astralsorcery:cap_item_amulet_holder":{}},id:"projecte:item.pe_transmutation_tablet",Count:1b,Damage:0s},{Slot:7b,id:"harvestcraft:candledeco1",Count:64b,Damage:0s},{Slot:8b,ForgeCaps:{"astralsorcery:cap_item_amulet_holder":{}},id:"spiceoflife:lunchbox",Count:1b,tag:{UUID:"2817a286-02d8-4df4-97b3-b82dfb34c78c",Inventory:{Items:[{Slot:0b,id:"harvestcraft:duckcookeditem",Count:13b,Damage:0s},{Slot:1b,id:"minecraft:cooked_chicken",Count:12b,Damage:0s},{Slot:2b,id:"minecraft:cooked_beef",Count:12b,Damage:0s},{Slot:3b,id:"harvestcraft:turkeycookeditem",Count:10b,Damage:0s},{Slot:5b,id:"harvestcraft:venisoncookeditem",Count:8b,Damage:0s}]},Open:1b},Damage:0s},{Slot:9b,id:"minecraft:cobblestone",Count:64b,Damage:0s},{Slot:10b,id:"minecraft:cobblestone",Count:64b,Damage:0s},{Slot:11b,id:"minecraft:cobblestone",Count:64b,Damage:0s},{Slot:12b,id:"minecraft:dirt",Count:1b,Damage:0s},{Slot:13b,id:"minecraft:cobblestone",Count:64b,Damage:0s},{Slot:14b,id:"minecraft:cobblestone",Count:64b,Damage:0s},{Slot:15b,id:"minecraft:cobblestone",Count:64b,Damage:0s},{Slot:16b,id:"minecraft:stick",Count:4b,Damage:0s},{Slot:17b,ForgeCaps:{"astralsorcery:cap_item_amulet_holder":{}},id:"minecraft:chainmail_helmet",Count:1b,Damage:0s},{Slot:18b,id:"minecraft:gold_ingot",Count:1b,Damage:0s},{Slot:19b,id:"minecraft:cobblestone",Count:64b,Damage:0s},{Slot:20b,id:"minecraft:cobblestone",Count:64b,Damage:0s},{Slot:21b,id:"minecraft:cobblestone",Count:64b,Damage:0s},{Slot:22b,id:"xreliquary:interdiction_torch",Count:2b,Damage:0s},{Slot:23b,id:"minecraft:cobblestone",Count:35b,Damage:0s},{Slot:35b,id:"thaumcraft:phial",Count:1b,tag:{Aspects:[{amount:10,key:"aversio"}]},Damage:1s},{Slot:36b,ForgeCaps:{"astralsorcery:cap_item_amulet_holder":{AS_Amulet_HolderLeast:-7555183444744161111L,AS_Amulet_HolderMost:5323732677059037779L}},id:"minecraft:diamond_boots",Count:1b,tag:{ench:[{lvl:1s,id:59s}]},Damage:59s},{Slot:37b,ForgeCaps:{"astralsorcery:cap_item_amulet_holder":{AS_Amulet_HolderLeast:-7555183444744161111L,AS_Amulet_HolderMost:5323732677059037779L}},id:"minecraft:iron_leggings",Count:1b,Damage:146s},{Slot:38b,ForgeCaps:{"astralsorcery:cap_item_amulet_holder":{AS_Amulet_HolderLeast:-7555183444744161111L,AS_Amulet_HolderMost:5323732677059037779L}},id:"minecraft:iron_chestplate",Count:1b,Damage:146s},{Slot:39b,ForgeCaps:{"astralsorcery:cap_item_amulet_holder":{AS_Amulet_HolderLeast:-7555183444744161111L,AS_Amulet_HolderMost:5323732677059037779L}},id:"iceandfire:forest_troll_leather_helmet",Count:1b,Damage:59s}]}}