{IsEmpty:0b,InventoryHolder:{Zcoord:-388,cosmeticarmor:[],PlayerName:[],Ycoord:88,Xcoord:282,bauble:[],Timestamp:[],vanilla:[{Slot:0b,ForgeCaps:{"astralsorcery:cap_item_amulet_holder":{}},id:"thaumcraft:crimson_blade",Count:1b,tag:{ench:[{lvl:3s,id:21s}],RepairCost:1,pickletweaks:{EnemiesKilled:31,DamageDealt:739}},Damage:0s},{Slot:1b,ForgeCaps:{"astralsorcery:cap_item_amulet_holder":{}},id:"thermalfoundation:tool.bow_steel",Count:1b,tag:{ench:[{lvl:1s,id:51s}],pickletweaks:{EnemiesKilled:141,DamageDealt:3754}},Damage:550s},{Slot:2b,id:"thermalexpansion:morb",Count:1b,Damage:1s},{Slot:3b,id:"minecraft:iron_ingot",Count:5b,Damage:0s},{Slot:4b,id:"minecraft:diamond",Count:3b,Damage:0s},{Slot:5b,ForgeCaps:{"astralsorcery:cap_item_amulet_holder":{}},id:"minecraft:flint_and_steel",Count:1b,Damage:0s},{Slot:6b,id:"minecraft:saddle",Count:1b,Damage:0s},{Slot:7b,id:"extrautils2:ironwood_sapling",Count:1b,Damage:0s},{Slot:9b,id:"minecraft:blaze_rod",Count:10b,Damage:0s},{Slot:11b,ForgeCaps:{"astralsorcery:cap_item_amulet_holder":{}},id:"xreliquary:angelic_feather",Count:1b,Damage:0s},{Slot:12b,id:"xreliquary:interdiction_torch",Count:3b,Damage:0s},{Slot:13b,ForgeCaps:{"astralsorcery:cap_item_amulet_holder":{}},id:"minecraft:golden_sword",Count:1b,tag:{ench:[{lvl:1s,id:21s}]},Damage:15s},{Slot:14b,ForgeCaps:{"astralsorcery:cap_item_amulet_holder":{}},id:"astralsorcery:itemwand",Count:1b,tag:{astralsorcery:{AugmentName:"astralsorcery.constellation.evorsio"}},Damage:0s},{Slot:15b,ForgeCaps:{"astralsorcery:cap_item_amulet_holder":{}},id:"minecraft:iron_leggings",Count:1b,Damage:169s},{Slot:16b,id:"quark:black_ash",Count:2b,Damage:0s},{Slot:17b,ForgeCaps:{"astralsorcery:cap_item_amulet_holder":{}},id:"roughtweaks:salve",Count:1b,Damage:0s},{Slot:18b,id:"minecraft:nether_brick",Count:4b,Damage:0s},{Slot:19b,ForgeCaps:{"astralsorcery:cap_item_amulet_holder":{}},id:"roughtweaks:plaster",Count:1b,Damage:0s},{Slot:27b,id:"cyclicmagic:magnet_anti_block",Count:3b,Damage:0s},{Slot:28b,ForgeCaps:{"astralsorcery:cap_item_amulet_holder":{}},id:"thermalinnovation:magnet",Count:1b,tag:{Energy:239925,Filter:{Items:[],Flags:0b},Mode:1},Damage:2s},{Slot:29b,id:"minecraft:obsidian",Count:2b,Damage:0s},{Slot:30b,id:"minecraft:gold_ingot",Count:3b,Damage:0s},{Slot:31b,id:"minecraft:nether_wart",Count:4b,Damage:0s},{Slot:32b,ForgeCaps:{"astralsorcery:cap_item_amulet_holder":{}},id:"deepmoblearning:data_model_wither_skeleton",Count:1b,tag:{simulationCount:0,tier:1,killCount:0,totalKillCount:6},Damage:0s},{Slot:34b,ForgeCaps:{"astralsorcery:cap_item_amulet_holder":{}},id:"thermalfoundation:wrench",Count:1b,Damage:0s}]}}